smslib/__init__.py
smslib/api.py
smslib/tests.py
smsapi_lib-0.1.0.dist-info/METADATA
smsapi_lib-0.1.0.dist-info/WHEEL
smsapi_lib-0.1.0.dist-info/top_level.txt
smsapi_lib-0.1.0.dist-info/RECORD
