Metadata-Version: 2.4
Name: smsapi_lib
Version: 0.1.0
Summary: Add your description here
Requires-Python: >=3.11
Requires-Dist: httpx>=0.28.1
Requires-Dist: orjson>=3.11.1
Requires-Dist: polars[all]>=1.32.2
Requires-Dist: sphinx>=8.2.3
Requires-Dist: sphinx-autodoc-typehints>=3.2.0
Requires-Dist: sphinx-rtd-theme>=3.0.2
